patch/__init__.py
patch/types.py
python_patch-0.0.1.dist-info/LICENSE
python_patch-0.0.1.dist-info/WHEEL
python_patch-0.0.1.dist-info/METADATA
python_patch-0.0.1.dist-info/RECORD
